README
setup.py
timeline_django/__init__.py
timeline_django/filters.py
timeline_django/hooks.py
timeline_django/setup.py
timeline_django/signals.py
timeline_django/test_settings.py
timeline_django/timeline_cursor.py
timeline_django/wsgi.py
timeline_django.egg-info/PKG-INFO
timeline_django.egg-info/SOURCES.txt
timeline_django.egg-info/dependency_links.txt
timeline_django.egg-info/requires.txt
timeline_django.egg-info/top_level.txt
timeline_django/tests/__init__.py
timeline_django/tests/test_filters.py
timeline_django/tests/test_hooks.py
timeline_django/tests/test_timeline_cursor.py
timeline_django/tests/test_wsgi.py