Metadata-Version: 1.1
Name: timeline-django
Version: 0.0.3
Summary: Insert Django database queries in to a Timeline
Home-page: http://launchpad.net/python-timeline-django
Author: Launchpad developers
Author-email: launchpad-dev@lists.launchpad.net
License: LGPLv3
Download-URL: https://launchpad.net/python-timeline-django/+download
Platform: UNKNOWN
